huber/__init__.py
huber/driver.py
huber/faults.csv
huber/mock.py
huber/util.py
huber-0.8.1.dist-info/LICENSE
huber-0.8.1.dist-info/METADATA
huber-0.8.1.dist-info/WHEEL
huber-0.8.1.dist-info/entry_points.txt
huber-0.8.1.dist-info/top_level.txt
huber-0.8.1.dist-info/RECORD
