Metadata-Version: 2.1
Name: huber
Version: 0.8.1
Summary: Python driver for Huber recirculating baths.
Author-email: Pat Fuller <patrickfuller@gmail.com>
Maintainer-email: Alex Ruddick <alex@ruddick.tech>
Project-URL: Homepage, https://github.com/alexrudd2/huber
Project-URL: Issues, https://github.com/alexrudd2/huber/issues
Classifier: License :: OSI Approved :: GNU General Public License v2 (GPLv2)
Classifier: Development Status :: 4 - Beta
Classifier: Natural Language :: English
Classifier: Programming Language :: Python
Classifier: Programming Language :: Python :: 3
Classifier: Programming Language :: Python :: 3.9
Classifier: Programming Language :: Python :: 3.10
Classifier: Programming Language :: Python :: 3.11
Classifier: Programming Language :: Python :: 3.12
Classifier: Programming Language :: Python :: 3.13
Classifier: Topic :: Scientific/Engineering :: Human Machine Interfaces
Classifier: Topic :: Scientific/Engineering :: Electronic Design Automation (EDA)
License-File: LICENSE
Provides-Extra: test
Requires-Dist: mypy ==1.13.0 ; extra == 'test'
Requires-Dist: pytest ; extra == 'test'
Requires-Dist: pytest-cov ; extra == 'test'
Requires-Dist: pytest-asyncio ; extra == 'test'
Requires-Dist: ruff ==0.7.2 ; extra == 'test'
